{
  "name": "Hullbreaker",
  "stats": {
    "attack_damage": {
      "value": 50,
      "type": "flat"
    },
    "health": {
      "value": 400,
      "type": "flat"
    },
    "ability_haste": {
      "value": 15,
      "type": "flat"
    },
    "armor": {
      "value": 130,
      "type": "flat"
    },
    "magic_resist": {
      "value": 120,
      "type": "flat"
    }
  },
  "cost": 3200,
  "passive": "Boarding Party: While no allied champions are nearby, gain 20% increased damage to structures and 20 Armor and Magic Resist. Nearby minions gain 60% increased damage to structures and take 75% reduced damage from champions and structures.",
  "active": "",
  "description": "Split-push focused item that provides Attack Damage, Health, and Ability Haste. When isolated from allies, grants bonus resistances and structure damage while empowering nearby minions. Perfect for split-pushers who want to pressure side lanes and take towers quickly while being harder to kill when caught alone.",
  "category": "legendary",
  "tier": "A",
  "build_path": [
    "Phage",
    "Caulfield's Warhammer"
  ],
  "tags": [
    "Damage",
    "Physical",
    "Health",
    "Ability Haste",
    "Split Push",
    "Structure Damage"
  ],
  "tips": [
    "Best used by champions who can split-push effectively like Fiora, Jax, or Tryndamere",
    "The isolation bonus makes you tankier when caught alone - great for 1v1 duels",
    "Empowered minions help take towers faster and draw enemy attention",
    "Great for drawing enemy attention to side lanes while your team groups",
    "The 20 bonus resistances when isolated can be the difference in close fights"
  ],
  "build_components": {},
  "builds_into": []
}